Metadata-Version: 2.1
Name: compara-preco-litro
Version: 0.0.1
Summary: Compara preço por litro a partir de um arquivo .txt
Author: pedro_oliveira
Author-email: pedro.oliveirape@hotmail.com
Requires-Python: >=3.8
